{"actions":null,"author":"","autostart":true,"color_coding":false,"dice":"D6","distribution_mode":null,"height":null,"interval":1,"multiplayer":"","name":"","nodes":[{"actions":1,"activation_mode":0,"capacity":-1,"caption":"","caption_pos":null,"color":0,"emit_state_changed":false,"name":"editor_pool","pull_mode":0,"resource_color":0,"starting_resources":0,"thickness":2,"type":2,"x":337.733337,"y":209.222229},{"actions":1,"activation_mode":0,"capacity":-1,"caption":"","caption_pos":null,"color":0,"emit_state_changed":false,"name":"@editor_pool@218","pull_mode":0,"resource_color":0,"starting_resources":0,"thickness":2,"type":2,"x":486.533356,"y":241.444458},{"actions":1,"activation_mode":0,"capacity":-1,"caption":"","caption_pos":null,"color":0,"emit_state_changed":false,"name":"@editor_pool@219","pull_mode":0,"resource_color":0,"starting_resources":0,"thickness":2,"type":2,"x":375.066681,"y":411.444458}],"number_of_runs":null,"skill":"","speed":null,"strategy":"","time_mode":null,"version":null,"visible_runs":null,"width":null}